danger_py_cov/__init__.py
danger_py_cov/calculations.py
danger_py_cov/cobertura.py
danger_py_cov/models.py
danger_py_cov/plugin.py
danger_py_cov/report.py
danger_py_cov/templates/report.md.jinja
danger_py_cov-0.1.0.dist-info/LICENSE
danger_py_cov-0.1.0.dist-info/WHEEL
danger_py_cov-0.1.0.dist-info/METADATA
danger_py_cov-0.1.0.dist-info/RECORD
