Metadata-Version: 2.1
Name: danger-py-cov
Version: 0.1.0
Summary: danger-python plugin for displaying code coverage changes
Author: Jakub Turek
Author-email: jkbturek@gmail.com
Requires-Python: >=3.7,<4.0
Classifier: Programming Language :: Python :: 3
Classifier: Programming Language :: Python :: 3.7
Classifier: Programming Language :: Python :: 3.8
Requires-Dist: jinja2 (>=2.11.1,<3.0.0)
Requires-Dist: pycobertura (>=0.10.5,<0.11.0)
